{"miraji words": [1, "/categories/miraji-words.html", {"posts": [{"date": "02/11/2014", "url": "/posts/mirajis-favorite-words.html", "isodate": "2014-02-11T10:53:04+00:00", "title": "Miraji\u2019s Favorite Words"}]}], "hindi urdu translation css": [1, "/categories/hindi-urdu-translation-css.html", {"posts": [{"date": "02/04/2014", "url": "/posts/added-hindi-and-urdu.html", "isodate": "2014-02-04T20:30:41+00:00", "title": "Added Hindi and Urdu"}]}], "art": [1, "/categories/art.html", {"posts": [{"date": "03/26/2014", "url": "/posts/book-cover.html", "isodate": "2014-03-26T20:31:04+00:00", "title": "Book Cover"}]}], "blogging": [1, "/categories/blogging.html", {"posts": [{"date": "01/28/2014", "url": "/posts/welcome-to-my-blog.html", "isodate": "2014-01-28T07:06:17+00:00", "title": "Welcome to My Blog"}]}], "academic": [1, "/categories/academic.html", {"posts": [{"date": "01/28/2014", "url": "/posts/welcome-to-my-blog.html", "isodate": "2014-01-28T07:06:17+00:00", "title": "Welcome to My Blog"}]}]}